Metadata-Version: 1.1
Name: plocustio
Version: 0.11.1.3
Summary: Website load testing framework
Home-page: https://locust.io/
Author: Jonatan Heyman, Carl Bystrom, Joakim Hamrén, Hugo Heyman
Author-email: UNKNOWN
License: MIT
Platform: UNKNOWN
Classifier: Topic :: Software Development :: Testing :: Traffic Generation
Classifier: Development Status :: 4 - Beta
Classifier: License :: OSI Approved :: MIT License
Classifier: Operating System :: OS Independent
Classifier: Programming Language :: Python
Classifier: Programming Language :: Python :: 2
Classifier: Programming Language :: Python :: 2.7
Classifier: Programming Language :: Python :: 3
Classifier: Programming Language :: Python :: 3.5
Classifier: Programming Language :: Python :: 3.6
Classifier: Programming Language :: Python :: 3.7
Classifier: Intended Audience :: Developers
Classifier: Intended Audience :: System Administrators
